COPYING
MANIFEST.in
README
__pkginfo__.py
logilab_grutils.py
setup.py
bin/gmmerge
bin/grmerge
bin/ingrsh
bin/ingrsh.zsh
bin/jobtest
bin/nicetests
bin/pygrep
bin/tagsmerge
elisp/changelog.el
elisp/logilab.el
elisp/pycover-mode.el
elisp/startup
hgext/__init__.py
hgext/jpl/__init__.py
hgext/jpl/apycot.py
hgext/jpl/jplproxy.py
hgext/jpl/review.py
hgext/jpl/tasks.py
logilab_devtools.egg-info/PKG-INFO
logilab_devtools.egg-info/SOURCES.txt
logilab_devtools.egg-info/dependency_links.txt
logilab_devtools.egg-info/namespace_packages.txt
logilab_devtools.egg-info/requires.txt
logilab_devtools.egg-info/top_level.txt