Metadata-Version: 1.1
Name: logilab-devtools
Version: 0.26.0
Summary: set of development tools used at Logilab
Home-page: http://www.logilab.org/project/logilab-devtools
Author: Logilab
Author-email: contact@logilab.fr
License: GPL
Platform: UNKNOWN
Classifier: Development Status :: 3 - Alpha
Classifier: Intended Audience :: Developers
Classifier: Topic :: Software Development :: Build Tools
Classifier: License :: OSI Approved :: GNU General Public License v2 (GPLv2)
Classifier: Programming Language :: Python :: 2
Classifier: Programming Language :: Python :: 2.6
Classifier: Programming Language :: Python :: 2.7
